{
    "fluentMethods": true,
    "relationships": [],
    "fields": [
        {
            "fieldName": "changeReason",
            "fieldType": "String",
            "fieldValidateRules": [
                "maxlength"
            ],
            "fieldValidateRulesMaxlength": "1024"
        },
        {
            "fieldName": "changeType",
            "fieldType": "String",
            "fieldValidateRules": [
                "required",
                "maxlength"
            ],
            "fieldValidateRulesMaxlength": 20
        },
        {
            "fieldName": "whetherFreezingAndThawing",
            "fieldType": "Boolean"
        },
        {
            "fieldName": "operatorId1",
            "fieldType": "Long"
        },
        {
            "fieldName": "operatorId2",
            "fieldType": "Long"
        },
        {
            "fieldName": "status",
            "fieldType": "String",
            "fieldValidateRules": [
                "required",
                "maxlength"
            ],
            "fieldValidateRulesMaxlength": "20"
        },
        {
            "fieldName": "memo",
            "fieldType": "String",
            "fieldValidateRules": [
                "maxlength"
            ],
            "fieldValidateRulesMaxlength": "1024"
        }
    ],
    "changelogDate": "20170803011622",
    "dto": "mapstruct",
    "service": "serviceImpl",
    "entityTableName": "position_change",
    "pagination": "pager",
    "enableEntityAudit": true
}
